{
  "currency": "USD",
  "exchange": "NMS",
  "quote_type": "EQUITY",
  "raw": {
    "currency": "USD",
    "dayHigh": 323.29998779296875,
    "dayLow": 319.3500061035156,
    "exchange": "NMS",
    "fiftyDayAverage": 304.88739990234376,
    "lastPrice": 322.04998779296875,
    "lastVolume": 10897578,
    "marketCap": 4730062820510.986,
    "open": 321.7300109863281,
    "previousClose": 325.74,
    "quoteType": "EQUITY",
    "regularMarketPreviousClose": 325.8900146484375,
    "shares": 14687356000,
    "tenDayAverageVolume": 48269410,
    "threeMonthAverageVolume": 54887251,
    "timezone": "America/New_York",
    "twoHundredDayAverage": 275.2805994415283,
    "yearChange": 0.5245603621963777,
    "yearHigh": 334.989990234375,
    "yearLow": 201.5
  },
  "ticker": "AAPL",
  "timezone": "America/New_York"
}